challenge_mcp/__init__.py
challenge_mcp/authfastmcp.py
challenge_mcp/server.py
challenge_mcp-0.1.1.dist-info/METADATA
challenge_mcp-0.1.1.dist-info/WHEEL
challenge_mcp-0.1.1.dist-info/RECORD
