Metadata-Version: 2.4
Name: challenge-mcp
Version: 0.1.1
Summary: A Model Context Protocol server for challenge management with authentication
Project-URL: Homepage, https://github.com/your-username/challenge-mcp
Project-URL: Documentation, https://challenge-mcp.readthedocs.io
Project-URL: Repository, https://github.com/your-username/challenge-mcp.git
Project-URL: Bug Tracker, https://github.com/your-username/challenge-mcp/issues
Project-URL: Changelog, https://github.com/your-username/challenge-mcp/blob/main/CHANGELOG.md
Author-email: Challenge MCP Team <team@challenge-mcp.com>
Maintainer-email: Challenge MCP Team <team@challenge-mcp.com>
License: MIT
Keywords: authentication,challenge,fastapi,mcp,model-context-protocol,server
Classifier: Development Status :: 3 - Alpha
Classifier: Framework :: FastAPI
Classifier: Intended Audience :: Developers
Classifier: License :: OSI Approved :: MIT License
Classifier: Operating System :: OS Independent
Classifier: Programming Language :: Python :: 3
Classifier: Programming Language :: Python :: 3.11
Classifier: Programming Language :: Python :: 3.12
Classifier: Programming Language :: Python :: 3.13
Classifier: Topic :: Internet :: WWW/HTTP :: HTTP Servers
Classifier: Topic :: Software Development :: Libraries :: Python Modules
Requires-Python: >=3.11
Requires-Dist: httpx-sse>=0.4.0
Requires-Dist: httpx>=0.28.0
Requires-Dist: mcp[cli]>=1.6.0
Requires-Dist: pydantic-settings>=2.9.0
Requires-Dist: pydantic>=2.11.0
Requires-Dist: python-dotenv>=1.1.0
Requires-Dist: python-multipart>=0.0.20
Requires-Dist: sse-starlette>=2.3.0
Requires-Dist: starlette>=0.46.0
Requires-Dist: uvicorn>=0.34.0
Provides-Extra: dev
Requires-Dist: black>=23.0.0; extra == 'dev'
Requires-Dist: flake8>=6.0.0; extra == 'dev'
Requires-Dist: isort>=5.12.0; extra == 'dev'
Requires-Dist: mypy>=1.0.0; extra == 'dev'
Requires-Dist: pytest-asyncio>=0.21.0; extra == 'dev'
Requires-Dist: pytest-cov>=4.0.0; extra == 'dev'
Requires-Dist: pytest>=7.0.0; extra == 'dev'
Provides-Extra: docs
Requires-Dist: mkdocs-material>=9.0.0; extra == 'docs'
Requires-Dist: mkdocs>=1.5.0; extra == 'docs'
Requires-Dist: mkdocstrings[python]>=0.20.0; extra == 'docs'
